opencloudtool-0.6.0.dist-info/METADATA
opencloudtool-0.6.0.dist-info/WHEEL
opencloudtool/__init__.py
opencloudtool/_internal.cpython-312-darwin.so
opencloudtool/py_api.py
opencloudtool-0.6.0.dist-info/RECORD
