Metadata-Version: 2.4
Name: opencloudtool
Version: 0.6.0
Requires-Python: >=3.8
